riffq-0.1.7.dist-info/METADATA
riffq-0.1.7.dist-info/WHEEL
riffq-0.1.7.dist-info/licenses/LICENSE-APACHE
riffq-0.1.7.dist-info/licenses/LICENSE-MIT
riffq/__init__.py
riffq/_riffq.cpython-312-x86_64-linux-gnu.so
riffq/connection.py
riffq/helpers.py
riffq-0.1.7.dist-info/RECORD
