Metadata-Version: 2.4
Name: riffq
Version: 0.1.7
Classifier: Programming Language :: Rust
Requires-Dist: pyarrow
License-File: LICENSE-APACHE
License-File: LICENSE-MIT
Summary: riffq is a toolkit for building PostgreSQL wire-compatible databases. Think exposing pandas/polars dataframe or duckdb with PostgreSQL wire protocol with pg_catalog compatibility.
Requires-Python: >=3.8
